custommediatool/__init__.py
custommediatool/code/media_filtering.py
custommediatool/code/media_pipeline.py
custommediatool/code/media_retrieval.py
custommediatool/resources/marine_life_sea_sports_related_words.pkl
custommediatool/resources/non_maritime_words.pkl
custommediatool/resources/stop_words_v1.pkl
custommediatool/resources/Word2Vec Trained Model/w2v_model.model
custommediatool-0.1.0.dist-info/METADATA
custommediatool-0.1.0.dist-info/WHEEL
custommediatool-0.1.0.dist-info/RECORD
