Metadata-Version: 2.1
Name: custommediatool
Version: 0.1.0
Summary: Retrieving targeted media news about dredging, specific dredging projects, and news about competitors within the dredging industry.
License: Boskalis
Author: Mariam Safieldin
Author-email: mariam.safieldin@boskalis.com
Requires-Python: >=3.8,<4.0
Classifier: License :: Other/Proprietary License
Classifier: Programming Language :: Python :: 3
Classifier: Programming Language :: Python :: 3.8
Classifier: Programming Language :: Python :: 3.9
Classifier: Programming Language :: Python :: 3.10
Classifier: Programming Language :: Python :: 3.11
Requires-Dist: azure-cognitiveservices-search-newssearch (==2.0.0)
Requires-Dist: azure-data-tables (==12.4.3)
Requires-Dist: beautifulsoup4 (==4.12.2)
Requires-Dist: deep-translator (==1.11.4)
Requires-Dist: eventregistry (==9.1)
Requires-Dist: gensim (==4.3.1)
Requires-Dist: langdetect (==1.0.9)
Requires-Dist: nltk (==3.6.3)
Requires-Dist: pandas (==1.5.3)
Requires-Dist: python-dotenv (==1.0.0)
Requires-Dist: requests (==2.31.0)
